LICENCE.txt
README.rst
bootstrap.py
flavour-development.cfg
setup.py
virtualbox.rst
ezjailremote/__init__.py
ezjailremote/fabfile.py
ezjailremote/utils.py
ezjailremote.egg-info/PKG-INFO
ezjailremote.egg-info/SOURCES.txt
ezjailremote.egg-info/dependency_links.txt
ezjailremote.egg-info/entry_points.txt
ezjailremote.egg-info/not-zip-safe
ezjailremote.egg-info/requires.txt
ezjailremote.egg-info/top_level.txt
ezjailremote/flavours/__init__.py
ezjailremote/flavours/basic/__init__.py
ezjailremote/flavours/basic/ezjail.flavour
ezjailremote/flavours/basic/etc/make.conf
ezjailremote/flavours/basic/etc/periodic.conf
ezjailremote/flavours/basic/etc/rc.conf
ezjailremote/flavours/basic/etc/resolv.conf
ezjailremote/flavours/basic/usr/local/etc/sudoers
ezjailremote/tests/__init__.py
ezjailremote/tests/test_docstrings.py