Metadata-Version: 1.1
Name: ezjailremote
Version: 0.2.2
Summary: a remote control and convenience wrapper for ezjail
Home-page: https://github.com/tomster/ezjail-remote
Author: Tom Lazar
Author-email: tom@tomster.org
License: BSD
Keywords: ezjail,FreeBSD,fabric
Platform: UNKNOWN
Classifier: Development Status :: 4 - Beta
Classifier: Environment :: Console
Classifier: Intended Audience :: System Administrators
Classifier: License :: OSI Approved :: BSD License
Classifier: Operating System :: POSIX :: BSD :: FreeBSD
Classifier: Programming Language :: Python
Classifier: Topic :: System :: Systems Administration
